{"assets/images/.DS_Store":["assets/images/.DS_Store"],"assets/images/adobe.png":["assets/images/adobe.png"],"assets/images/atmcard.png":["assets/images/atmcard.png"],"assets/images/atomhelp.png":["assets/images/atomhelp.png"],"assets/images/atomlogo.png":["assets/images/atomlogo.png"],"assets/images/avatar.jpeg":["assets/images/avatar.jpeg"],"assets/images/backgroundimage.png":["assets/images/backgroundimage.png"],"assets/images/blackcard.png":["assets/images/blackcard.png"],"assets/images/emergency.png":["assets/images/emergency.png"],"assets/images/find.png":["assets/images/find.png"],"assets/images/findus.png":["assets/images/findus.png"],"assets/images/graph.png":["assets/images/graph.png"],"assets/images/greencard.png":["assets/images/greencard.png"],"assets/images/help.png":["assets/images/help.png"],"assets/images/house.png":["assets/images/house.png"],"assets/images/income.png":["assets/images/income.png"],"assets/images/internet.png":["assets/images/internet.png"],"assets/images/johndoe.png":["assets/images/johndoe.png"],"assets/images/macm1.png":["assets/images/macm1.png"],"assets/images/main.png":["assets/images/main.png"],"assets/images/month.png":["assets/images/month.png"],"assets/images/more.png":["assets/images/more.png"],"assets/images/outcome.png":["assets/images/outcome.png"],"assets/images/pay.png":["assets/images/pay.png"],"assets/images/paypal.png":["assets/images/paypal.png"],"assets/images/privacy.png":["assets/images/privacy.png"],"assets/images/profile.png":["assets/images/profile.png"],"assets/images/promo.png":["assets/images/promo.png"],"assets/images/qrscan.png":["assets/images/qrscan.png"],"assets/images/request.png":["assets/images/request.png"],"assets/images/savebutton.png":["assets/images/savebutton.png"],"assets/images/security.png":["assets/images/security.png"],"assets/images/send.png":["assets/images/send.png"],"assets/images/spotify.png":["assets/images/spotify.png"],"assets/images/transfer.png":["assets/images/transfer.png"],"assets/images/transfer2.png":["assets/images/transfer2.png"],"assets/images/vacjapan.png":["assets/images/vacjapan.png"],"assets/images/whitecard.png":["assets/images/whitecard.png"],"packages/cupertino_icons/assets/CupertinoIcons.ttf":["packages/cupertino_icons/assets/CupertinoIcons.ttf"]}